aerotransport/__init__.py
aerotransport/core.py
aerotransport/exceptions.py
aerotransport/utils.py
aerotransport/models/__init__.py
aerotransport/models/airplane.py
aerotransport/models/airport.py
aerotransport/models/flight.py
aerotransport-0.1.0.dist-info/licenses/LICENSE
aerotransport-0.1.0.dist-info/METADATA
aerotransport-0.1.0.dist-info/WHEEL
aerotransport-0.1.0.dist-info/top_level.txt
aerotransport-0.1.0.dist-info/RECORD
