Metadata-Version: 2.4
Name: aerotransport
Version: 0.1.0
Summary: Librería para estimar tiempos y consumo de vuelos entre aeropuertos.
Author-email: Álvaro Fernández Villar <alvarofv.ing.aeronautico@gmail.com>
License: MIT
Classifier: Programming Language :: Python :: 3
Classifier: License :: OSI Approved :: MIT License
Classifier: Operating System :: OS Independent
Requires-Python: >=3.7
License-File: LICENSE
Requires-Dist: geopy>=2.3.0
Dynamic: license-file
